eegducks/__init__.py
eegducks/pipeline.py
eegducks-0.1.3.dist-info/METADATA
eegducks-0.1.3.dist-info/WHEEL
eegducks-0.1.3.dist-info/top_level.txt
eegducks-0.1.3.dist-info/RECORD
