Metadata-Version: 2.4
Name: eegducks
Version: 0.1.3
Summary: A beginner-friendly EEG wrapper around MNE
Author-email: Your Name <you@example.com>
Requires-Python: >=3.8
Requires-Dist: mne
